pywebwrap/__init__.py
pywebwrap/pywebwrap.py
venv/__init__.py
venv/Lib/__init__.py
venv/Lib/site-packages/__init__.py
venv/Lib/site-packages/_virtualenv.py
venv/Lib/site-packages/PyQt5/__init__.py
venv/Lib/site-packages/PyQt5/pylupdate_main.py
venv/Lib/site-packages/PyQt5/pyrcc_main.py
venv/Lib/site-packages/PyQt5/uic/__init__.py
venv/Lib/site-packages/PyQt5/uic/driver.py
venv/Lib/site-packages/PyQt5/uic/exceptions.py
venv/Lib/site-packages/PyQt5/uic/icon_cache.py
venv/Lib/site-packages/PyQt5/uic/objcreator.py
venv/Lib/site-packages/PyQt5/uic/properties.py
venv/Lib/site-packages/PyQt5/uic/pyuic.py
venv/Lib/site-packages/PyQt5/uic/uiparser.py
venv/Lib/site-packages/PyQt5/uic/Compiler/__init__.py
venv/Lib/site-packages/PyQt5/uic/Compiler/compiler.py
venv/Lib/site-packages/PyQt5/uic/Compiler/indenter.py
venv/Lib/site-packages/PyQt5/uic/Compiler/misc.py
venv/Lib/site-packages/PyQt5/uic/Compiler/proxy_metaclass.py
venv/Lib/site-packages/PyQt5/uic/Compiler/qobjectcreator.py
venv/Lib/site-packages/PyQt5/uic/Compiler/qtproxies.py
venv/Lib/site-packages/PyQt5/uic/Loader/__init__.py
venv/Lib/site-packages/PyQt5/uic/Loader/loader.py
venv/Lib/site-packages/PyQt5/uic/Loader/qobjectcreator.py
venv/Lib/site-packages/PyQt5/uic/port_v2/__init__.py
venv/Lib/site-packages/PyQt5/uic/port_v2/as_string.py
venv/Lib/site-packages/PyQt5/uic/port_v2/ascii_upper.py
venv/Lib/site-packages/PyQt5/uic/port_v2/proxy_base.py
venv/Lib/site-packages/PyQt5/uic/port_v2/string_io.py
venv/Lib/site-packages/PyQt5/uic/port_v3/__init__.py
venv/Lib/site-packages/PyQt5/uic/port_v3/as_string.py
venv/Lib/site-packages/PyQt5/uic/port_v3/ascii_upper.py
venv/Lib/site-packages/PyQt5/uic/port_v3/proxy_base.py
venv/Lib/site-packages/PyQt5/uic/port_v3/string_io.py
venv/Lib/site-packages/PyQt5/uic/widget-plugins/__init__.py
venv/Lib/site-packages/PyQt5/uic/widget-plugins/qaxcontainer.py
venv/Lib/site-packages/PyQt5/uic/widget-plugins/qscintilla.py
venv/Lib/site-packages/PyQt5/uic/widget-plugins/qtcharts.py
pywebwrap-0.0.13.dist-info/METADATA
pywebwrap-0.0.13.dist-info/WHEEL
pywebwrap-0.0.13.dist-info/top_level.txt
pywebwrap-0.0.13.dist-info/RECORD
