Metadata-Version: 2.1
Name: pywebwrap
Version: 0.0.13
Summary: Create desktop applications entirely using your favorite web technologies.
Author: Dekel Cohen
Author-email: <dcohen52@gmail.com>
Keywords: python,web,wrap,wrapper,desktop,html,javascript,css,js
Classifier: Development Status :: 1 - Planning
Classifier: Intended Audience :: Developers
Classifier: Programming Language :: Python :: 3
Classifier: Operating System :: Unix
Classifier: Operating System :: MacOS :: MacOS X
Classifier: Operating System :: Microsoft :: Windows
Requires-Dist: PyQt5
Requires-Dist: PyQtWebEngine
